foo8/__init__.py
foo8-0.1.0.dist-info/METADATA
foo8-0.1.0.dist-info/WHEEL
foo8-0.1.0.dist-info/RECORD
